[
  {
    "prevalence_id": "536",
    "orpha_code": "3099",
    "disease_name": "Rheumatic fever",
    "source": "21386976[PMID]_[EXPERT]",
    "prevalence_type": "Annual incidence",
    "prevalence_class": "1-9 / 100 000",
    "qualification": "Value and class",
    "geographic_area": "Latin America",
    "validation_status": "Validated",
    "reliability_score": 9.5,
    "is_fiable": true,
    "per_million_estimate": 50.0,
    "confidence_level": "high",
    "estimate_source": "class_midpoint"
  },
  {
    "prevalence_id": "597",
    "orpha_code": "15",
    "disease_name": "Achondroplasia",
    "source": "32803853[PMID]",
    "prevalence_type": "Prevalence at birth",
    "prevalence_class": "1-9 / 100 000",
    "qualification": "Value and class",
    "geographic_area": "Latin America",
    "validation_status": "Validated",
    "reliability_score": 9.8,
    "is_fiable": true,
    "per_million_estimate": 50.0,
    "confidence_level": "high",
    "estimate_source": "class_midpoint"
  },
  {
    "prevalence_id": "678",
    "orpha_code": "379",
    "disease_name": "Chronic granulomatous disease",
    "source": "17191150[PMID]_ORPHANET",
    "prevalence_type": "Prevalence at birth",
    "prevalence_class": "1-9 / 1 000 000",
    "qualification": "Value and class",
    "geographic_area": "Latin America",
    "validation_status": "Validated",
    "reliability_score": 9.8,
    "is_fiable": true,
    "per_million_estimate": 5.0,
    "confidence_level": "high",
    "estimate_source": "class_midpoint"
  },
  {
    "prevalence_id": "679",
    "orpha_code": "379",
    "disease_name": "Chronic granulomatous disease",
    "source": "17191150[PMID]_ORPHANET",
    "prevalence_type": "Point prevalence",
    "prevalence_class": "1-9 / 1 000 000",
    "qualification": "Class only",
    "geographic_area": "Latin America",
    "validation_status": "Validated",
    "reliability_score": 9.0,
    "is_fiable": true,
    "per_million_estimate": 5.0,
    "confidence_level": "high",
    "estimate_source": "class_midpoint"
  },
  {
    "prevalence_id": "896",
    "orpha_code": "2162",
    "disease_name": "Holoprosencephaly",
    "source": "17987642[PMID]",
    "prevalence_type": "Prevalence at birth",
    "prevalence_class": "1-5 / 10 000",
    "qualification": "Value and class",
    "geographic_area": "Latin America",
    "validation_status": "Validated",
    "reliability_score": 9.8,
    "is_fiable": true,
    "per_million_estimate": 300.0,
    "confidence_level": "high",
    "estimate_source": "class_midpoint"
  },
  {
    "prevalence_id": "1332",
    "orpha_code": "2655",
    "disease_name": "Thanatophoric dysplasia",
    "source": "22407836[PMID]",
    "prevalence_type": "Prevalence at birth",
    "prevalence_class": "1-9 / 100 000",
    "qualification": "Value and class",
    "geographic_area": "Latin America",
    "validation_status": "Validated",
    "reliability_score": 9.8,
    "is_fiable": true,
    "per_million_estimate": 50.0,
    "confidence_level": "high",
    "estimate_source": "class_midpoint"
  },
  {
    "prevalence_id": "1518",
    "orpha_code": "716",
    "disease_name": "Phenylketonuria",
    "source": "34082800[PMID]_ORPHANET",
    "prevalence_type": "Prevalence at birth",
    "prevalence_class": "1-9 / 100 000",
    "qualification": "Value and class",
    "geographic_area": "Latin America",
    "validation_status": "Validated",
    "reliability_score": 9.8,
    "is_fiable": true,
    "per_million_estimate": 50.0,
    "confidence_level": "high",
    "estimate_source": "class_midpoint"
  },
  {
    "prevalence_id": "1519",
    "orpha_code": "716",
    "disease_name": "Phenylketonuria",
    "source": "32668217[PMID]_ORPHANET",
    "prevalence_type": "Point prevalence",
    "prevalence_class": "1-9 / 100 000",
    "qualification": "Value and class",
    "geographic_area": "Latin America",
    "validation_status": "Validated",
    "reliability_score": 10.0,
    "is_fiable": true,
    "per_million_estimate": 50.0,
    "confidence_level": "high",
    "estimate_source": "class_midpoint"
  },
  {
    "prevalence_id": "1465",
    "orpha_code": "3169",
    "disease_name": "Sirenomelia",
    "source": "22002878[PMID]",
    "prevalence_type": "Prevalence at birth",
    "prevalence_class": "1-9 / 100 000",
    "qualification": "Value and class",
    "geographic_area": "Latin America",
    "validation_status": "Validated",
    "reliability_score": 9.8,
    "is_fiable": true,
    "per_million_estimate": 50.0,
    "confidence_level": "high",
    "estimate_source": "class_midpoint"
  },
  {
    "prevalence_id": "1692",
    "orpha_code": "666",
    "disease_name": "Osteogenesis imperfecta",
    "source": "3746832[PMID]",
    "prevalence_type": "Prevalence at birth",
    "prevalence_class": "1-9 / 1 000 000",
    "qualification": "Value and class",
    "geographic_area": "Latin America",
    "validation_status": "Validated",
    "reliability_score": 9.8,
    "is_fiable": true,
    "per_million_estimate": 5.0,
    "confidence_level": "high",
    "estimate_source": "class_midpoint"
  },
  {
    "prevalence_id": "12515",
    "orpha_code": "3389",
    "disease_name": "Tuberculosis",
    "source": "World Health Organization 2011[INST]",
    "prevalence_type": "Annual incidence",
    "prevalence_class": "1-5 / 10 000",
    "qualification": "Value and class",
    "geographic_area": "Latin America",
    "validation_status": "Validated",
    "reliability_score": 7.5,
    "is_fiable": true,
    "per_million_estimate": 300.0,
    "confidence_level": "high",
    "estimate_source": "class_midpoint"
  },
  {
    "prevalence_id": "9370",
    "orpha_code": "268369",
    "disease_name": "Open spinal dysraphism",
    "source": "3907353[PMID]",
    "prevalence_type": "Prevalence at birth",
    "prevalence_class": "6-9 / 10 000",
    "qualification": "Value and class",
    "geographic_area": "Latin America",
    "validation_status": "Validated",
    "reliability_score": 9.8,
    "is_fiable": true,
    "per_million_estimate": 750.0,
    "confidence_level": "high",
    "estimate_source": "class_midpoint"
  },
  {
    "prevalence_id": "4719",
    "orpha_code": "2968",
    "disease_name": "Leukocyte adhesion deficiency",
    "source": "22965369[PMID]",
    "prevalence_type": "Point prevalence",
    "prevalence_class": "<1 / 1 000 000",
    "qualification": "Class only",
    "geographic_area": "Latin America",
    "validation_status": "Not yet validated",
    "reliability_score": 6.0,
    "is_fiable": true,
    "per_million_estimate": 0.5,
    "confidence_level": "medium",
    "estimate_source": "class_estimate"
  },
  {
    "prevalence_id": "6035",
    "orpha_code": "70482",
    "disease_name": "Carcinoma of esophagus",
    "source": "ISBN:443075956[OTHER]_14530066[PMID]",
    "prevalence_type": "Annual incidence",
    "prevalence_class": "1-5 / 10 000",
    "qualification": "Value and class",
    "geographic_area": "Latin America",
    "validation_status": "Validated",
    "reliability_score": 9.5,
    "is_fiable": true,
    "per_million_estimate": 300.0,
    "confidence_level": "high",
    "estimate_source": "class_midpoint"
  },
  {
    "prevalence_id": "6935",
    "orpha_code": "88673",
    "disease_name": "Hepatocellular carcinoma",
    "source": "22537432[PMID]_18666317[PMID]_ ORPHANET",
    "prevalence_type": "Annual incidence",
    "prevalence_class": "1-5 / 10 000",
    "qualification": "Value and class",
    "geographic_area": "Latin America",
    "validation_status": "Validated",
    "reliability_score": 9.5,
    "is_fiable": true,
    "per_million_estimate": 300.0,
    "confidence_level": "high",
    "estimate_source": "class_midpoint"
  },
  {
    "prevalence_id": "7793",
    "orpha_code": "99745",
    "disease_name": "Typhoid",
    "source": "15298225[PMID]_World Health Organization[INST]",
    "prevalence_type": "Annual incidence",
    "prevalence_class": "1-5 / 10 000",
    "qualification": "Value and class",
    "geographic_area": "Latin America",
    "validation_status": "Validated",
    "reliability_score": 9.5,
    "is_fiable": true,
    "per_million_estimate": 300.0,
    "confidence_level": "high",
    "estimate_source": "class_midpoint"
  }
]